myDecorateTools_zhaozl/__init__.py
myDecorateTools_zhaozl/__version__.py
myDecorateTools_zhaozl/core.py
myDecorateTools_zhaozl-0.1.0.dist-info/LICENSE
myDecorateTools_zhaozl-0.1.0.dist-info/METADATA
myDecorateTools_zhaozl-0.1.0.dist-info/WHEEL
myDecorateTools_zhaozl-0.1.0.dist-info/top_level.txt
myDecorateTools_zhaozl-0.1.0.dist-info/RECORD
